xmltree2xml/__init__.py
xmltree2xml/main.py
xmltree2xml-0.1.2.dist-info/LICENSE
xmltree2xml-0.1.2.dist-info/METADATA
xmltree2xml-0.1.2.dist-info/WHEEL
xmltree2xml-0.1.2.dist-info/entry_points.txt
xmltree2xml-0.1.2.dist-info/top_level.txt
xmltree2xml-0.1.2.dist-info/RECORD
