Metadata-Version: 2.1
Name: xmltree2xml
Version: 0.1.2
Summary: convert compile xmltree file from android to classic xml
Home-page: https://github.com/remigermain/xmltree2xml
Author: rgermain
Author-email: contact@germainremi.fr
License: MIT
Project-URL: Bug Tracker, https://github.com/remigermain/xmltree2xml/issues
Classifier: Intended Audience :: Developers
Classifier: License :: OSI Approved :: BSD License
Classifier: Operating System :: OS Independent
Classifier: Programming Language :: Python
Classifier: Programming Language :: Python :: 3.6
Classifier: Programming Language :: Python :: 3.7
Classifier: Programming Language :: Python :: 3.8
Classifier: Programming Language :: Python :: 3.9
Classifier: Programming Language :: Python :: 3 :: Only
Requires-Python: >=3.6
License-File: LICENSE
